private_lecture_automation/data/introduction.html
private_lecture_automation/data/logo.png
private_lecture_automation/data/students.json.enc
private_lecture_automation/data/students_example.json
private_lecture_automation/__init__.py
private_lecture_automation/main.py
private_lecture_automation-0.2.0.dist-info/METADATA
private_lecture_automation-0.2.0.dist-info/WHEEL
private_lecture_automation-0.2.0.dist-info/licenses/LICENSE
private_lecture_automation-0.2.0.dist-info/RECORD
