Metadata-Version: 2.1
Name: private_lecture_automation
Version: 0.2.0
Summary: Automation tools for private lecture management.
Project-URL: Repository, https://github.com/PythonVilag/private-lecture-automation
Author-email: Daniel Mizsak <info@pythonvilag.hu>
License: MIT License
License-File: LICENSE
Keywords: automation,calendar event,introduction email,private lecture
Classifier: License :: OSI Approved :: MIT License
Classifier: Programming Language :: Python :: 3 :: Only
Classifier: Programming Language :: Python :: 3.8
Classifier: Programming Language :: Python :: 3.9
Classifier: Programming Language :: Python :: 3.10
Classifier: Programming Language :: Python :: 3.11
Classifier: Topic :: Home Automation
Requires-Python: >=3.8
Requires-Dist: icalendar==5.0.7
Requires-Dist: python-dotenv==1.0.0
Provides-Extra: dev
Requires-Dist: black; extra == 'dev'
Requires-Dist: furo; extra == 'dev'
Requires-Dist: hatch; extra == 'dev'
Requires-Dist: mypy; extra == 'dev'
Requires-Dist: pre-commit; extra == 'dev'
Requires-Dist: pytest; extra == 'dev'
Requires-Dist: pytest-cov; extra == 'dev'
Requires-Dist: ruff; extra == 'dev'
Requires-Dist: sphinx; extra == 'dev'
Requires-Dist: sphinx-copybutton; extra == 'dev'
